fepy/__init__.py
fepy-0.1.dist-info/DESCRIPTION.rst
fepy-0.1.dist-info/METADATA
fepy-0.1.dist-info/RECORD
fepy-0.1.dist-info/WHEEL
fepy-0.1.dist-info/metadata.json
fepy-0.1.dist-info/top_level.txt
