Metadata-Version: 2.0
Name: fepy
Version: 0.1
Summary: The python library for financial engineering
Home-page: https://github.com/eggachecat/fepy
Author: sunao
Author-email: sunao_0626@hotmail.com
License: MIT
Platform: UNKNOWN
